CHANGES.txt
LICENSE.txt
MANIFEST.in
README.txt
setup.py
src/djbuild/__init__.py
src/djbuild/dist_installer.py
src/djbuild/djbuild.py
src/djbuild/installer.py
src/djbuild/manage.py
src/djbuild/templates.py
src/djbuild/test.py
src/djbuild/tests.py
src/djbuild.egg-info/PKG-INFO
src/djbuild.egg-info/SOURCES.txt
src/djbuild.egg-info/dependency_links.txt
src/djbuild.egg-info/entry_points.txt
src/djbuild.egg-info/not-zip-safe
src/djbuild.egg-info/requires.txt
src/djbuild.egg-info/top_level.txt