Metadata-Version: 1.0
Name: djbuild
Version: 1.0.4
Summary: Buildout recipe for Django
Home-page: https://github.com/carlitux/djbuild
Author: Luis C. Cruz
Author-email: carlitos.kyo@gmail.com
License: BSD
Platform: UNKNOWN
Classifier: Framework :: Buildout
Classifier: Framework :: Django
Classifier: Topic :: Software Development :: Build Tools
Classifier: Development Status :: 4 - Beta
Classifier: License :: OSI Approved :: BSD License
